kommando_central/__init__.py
kommando_central/sql/initialize.sql
kommando_central/sql/schema.sql
kommando_central/static/style.css
kommando_central/static/images/CP-KB-logo.png
kommando_central/static/js/tab-navigation.js
kommando_central/templates/apidocs/dashboard.html.jinja
kommando_central/templates/auth/login.html.jinja
kommando_central/templates/base/base.html.jinja
kommando_central/templates/base/dashboard-page.html.jinja
kommando_central/templates/base/single-page.html.jinja
kommando_central/templates/events/dashboard.html.jinja
kommando_central/templates/tracks/dashboard.html.jinja
kommando_central/templates/tracks/register.html.jinja
kommando_central/templates/tracks/update.html.jinja
kommando_central/templates/users/dashboard.html.jinja
kommando_central/templates/users/register.html.jinja
kommando_central/templates/users/update.html.jinja
cpv_kommando_central-1.0.3.dist-info/METADATA
cpv_kommando_central-1.0.3.dist-info/WHEEL
cpv_kommando_central-1.0.3.dist-info/top_level.txt
cpv_kommando_central-1.0.3.dist-info/RECORD
